Products/PrintingMailHost/Patch.py
Products/PrintingMailHost/__init__.py
products_printingmailhost-2.0.1.dist-info/METADATA
products_printingmailhost-2.0.1.dist-info/WHEEL
products_printingmailhost-2.0.1.dist-info/top_level.txt
products_printingmailhost-2.0.1.dist-info/RECORD
