Metadata-Version: 2.4
Name: Products.PrintingMailHost
Version: 2.0.1
Summary: A monkey patch to send MailHost messages to standard out
Home-page: https://github.com/collective/Products.PrintingMailHost
Author: Martin Aspeli
Author-email: plone-developers@lists.sourceforge.net
License: GPL
Keywords: zope debug mailhost
Classifier: Development Status :: 5 - Production/Stable
Classifier: Framework :: Plone
Classifier: Framework :: Plone :: 6.2
Classifier: License :: OSI Approved :: GNU General Public License (GPL)
Classifier: Programming Language :: Python
Classifier: Programming Language :: Python :: 3.10
Classifier: Programming Language :: Python :: 3.11
Classifier: Programming Language :: Python :: 3.12
Classifier: Programming Language :: Python :: 3.13
Classifier: Topic :: Software Development :: Libraries :: Python Modules
Requires-Python: >=3.10
Requires-Dist: Products.MailHost
Requires-Dist: Zope
Dynamic: author
Dynamic: author-email
Dynamic: classifier
Dynamic: description
Dynamic: description-content-type
Dynamic: home-page
Dynamic: keywords
Dynamic: license
Dynamic: requires-dist
Dynamic: requires-python
Dynamic: summary
